streamlit_session_manager/__init__.py
streamlit_session_manager/session_manager.py
streamlit_session_manager-0.1.2.dist-info/LICENSE
streamlit_session_manager-0.1.2.dist-info/METADATA
streamlit_session_manager-0.1.2.dist-info/WHEEL
streamlit_session_manager-0.1.2.dist-info/top_level.txt
streamlit_session_manager-0.1.2.dist-info/RECORD
