Metadata-Version: 2.2
Name: streamlit-session-manager
Version: 0.1.2
Summary: A session manager for Streamlit applications
Home-page: https://github.com/5X-nextgen-customer-repo-prod/streamlit_session_manager.gitc
Author: 5X
Author-email: support@5x.co
License: MIT
Classifier: Programming Language :: Python :: 3.8
Classifier: Programming Language :: Python :: 3.9
Classifier: License :: OSI Approved :: MIT License
Classifier: Operating System :: OS Independent
Classifier: Development Status :: 3 - Alpha
Classifier: Intended Audience :: Developers
Classifier: Topic :: Software Development :: Libraries :: Python Modules
Requires-Python: >=3.8
License-File: LICENSE
Requires-Dist: extra-streamlit-components
Dynamic: author
Dynamic: author-email
Dynamic: classifier
Dynamic: description
Dynamic: description-content-type
Dynamic: home-page
Dynamic: license
Dynamic: requires-dist
Dynamic: requires-python
Dynamic: summary
